binary.py
binarylib.py
nodeweb.py
nodeweb/__init__.py
nodeweb/nodeweb.py
rabbit/__init__.py
rabbit/ascii码.py
rabbit/pyuse.py
rabbit/rabbit.py
rabbit/rabbitide.py
rabbit/setup.py
rabbit/列表.py
rabbit/基本.py
rabbit/字符串.py
rabbit/游戏.py
rabbit/终端.py
rabbit/绘图.py
rabbit/运算.py
nodeweb-1.0.3.dist-info/METADATA
nodeweb-1.0.3.dist-info/WHEEL
nodeweb-1.0.3.dist-info/top_level.txt
nodeweb-1.0.3.dist-info/RECORD
